djdb-1.2.0.dist-info/DESCRIPTION.rst
djdb-1.2.0.dist-info/METADATA
djdb-1.2.0.dist-info/RECORD
djdb-1.2.0.dist-info/WHEEL
djdb-1.2.0.dist-info/metadata.json
djdb-1.2.0.dist-info/top_level.txt
pydb/__init__.py
pydb/session.py
pydb/demo_db/__init__.py
pydb/demo_db/conf.py
pydb/demo_db/models.py
pydb/model/__init__.py
pydb/settings/__init__.py
pydb/settings/default_settings.py
