Metadata-Version: 2.0
Name: djdb
Version: 1.2.0
Summary: a python databases api
Home-page: https://github.com/HuangHongkai/pydb
Author: dfsss
Author-email: 2523272490@qq.com
License: UNKNOWN
Platform: UNKNOWN
Requires-Dist: Django (>=1.1.1)
